elfws/__init__.py
elfws/__main__.py
elfws/cmd_line_args.py
elfws/display.py
elfws/junit.py
elfws/suppression.py
elfws/suppression_list.py
elfws/utils.py
elfws/version.py
elfws/warning.py
elfws/warning_list.py
elfws/report/__init__.py
elfws/report/junit.py
elfws/subcommand/__init__.py
elfws/subcommand/create.py
elfws/subcommand/report.py
elfws/subcommand/show.py
elfws/subcommand/suppress.py
elfws/subcommand/version.py
elfws/vendor/__init__.py
elfws/vendor/utils.py
elfws/vendor/mentor_graphics/__init__.py
elfws/vendor/mentor_graphics/precision.py
elfws/vendor/mentor_graphics/questa_cdc__cdc_detail_rpt.py
elfws/vendor/mentor_graphics/questa_cdc__cdc_run_log.py
elfws/vendor/mentor_graphics/questa_lint.py
elfws/vendor/mentor_graphics/utils.py
elfws/vendor/microsemi/__init__.py
elfws/vendor/microsemi/designer.py
elfws/vendor/synopsys/__init__.py
elfws/vendor/synopsys/synplify_pro.py
elfws/vendor/xilinx/__init__.py
elfws/vendor/xilinx/vivado.py
elfws/vendor/xilinx/vivado_methodology.py
elfws-0.11.0.dist-info/LICENSE
elfws-0.11.0.dist-info/METADATA
elfws-0.11.0.dist-info/WHEEL
elfws-0.11.0.dist-info/entry_points.txt
elfws-0.11.0.dist-info/top_level.txt
elfws-0.11.0.dist-info/RECORD
