Metadata-Version: 2.1
Name: elfws
Version: 0.11.0
Summary: EDA Log File Warning Suppressor
Home-page: https://github.com/jeremiah-c-leary/eda-log-file-warning-suppressor
Download-URL: https://github.com/jeremiah-c-leary/eda-log-file-warning-suppressor
Author: Jeremiah C Leary
Author-email: jeremiah.c.leary@gmail.com
License: GNU General Public License
Keywords: eda,warning,suppression,logfile
Classifier: Development Status :: 4 - Beta
Classifier: Environment :: Console
Classifier: Programming Language :: Python :: 3
Classifier: Intended Audience :: End Users/Desktop
Classifier: License :: OSI Approved :: GNU General Public License v3 (GPLv3)
Classifier: Natural Language :: English
Classifier: Operating System :: POSIX :: Linux
Classifier: Topic :: Software Development :: Quality Assurance
Classifier: Topic :: Text Processing :: General
License-File: LICENSE
Requires-Dist: PyYAML
